todo_list_manager/__init__.py
todo_list_manager/tasks_creator.py
todo_list_manager/tasks_list_manager.py
simple_todo_list_manager-0.1.0.dist-info/METADATA
simple_todo_list_manager-0.1.0.dist-info/WHEEL
simple_todo_list_manager-0.1.0.dist-info/top_level.txt
simple_todo_list_manager-0.1.0.dist-info/RECORD
