Metadata-Version: 2.1
Name: simple-todo-list-manager
Version: 0.1.0
Summary: A package to create a simple To-Do list, save it as JSON file and manage it.
Home-page: UNKNOWN
Author: Friederike Lessmoellmann
Author-email: friederike.lessi@eweb.de
License: UNKNOWN
Platform: UNKNOWN
Classifier: Programming Language :: Python :: 3
Classifier: License :: OSI Approved :: MIT License
Classifier: Operating System :: OS Independent
Requires-Python: >=3.6
Requires-Dist: pathlib
Requires-Dist: string-color
